[{
	"title" : "后台首页",
	"icon" : "icon-computer",
	"href" : "page/main.jsp",
	"spread" : false
},{
	"title" : "帖子详情管理",
	"icon" : "icon-text",
	"href" : "page/news/newsList.jsp",
	"spread" : false
},{
	"title" : "用户信息管理",
	"icon" : "&#xe64c;",
	"href" : "page/links/linksList.jsp",
	"spread" : false
},{
	"title" : "用户审核",
	"icon" : "&#xe631;",
	"href" : "page/systemParameter/systemParameter.jsp",
	"spread" : false
},{
	"title" : "举报管理",
	"icon" : "&#xe61c;",
	"href" : "page/404.jsp",
	"spread" : false
},{
	"title" : "问题反馈",
	"icon" : "&#xe630;",
	"href" : "",
	"spread" : false,
	"children" : [
		{
			"title" : "未处理",
			"icon" : "&#xe609;",
			"href" : "/vhome/ShowQuestions?questions_status=0",
			"spread" : false
			
		},
		{
			"title" : "已处理",
			"icon" : "&#xe61c;",
			"href" : "/vhome/ShowQuestions?questions_status=1",
			"spread" : false
		}
	]
}
]